weblate/__init__.py
weblate/logger.py
weblate/middleware.py
weblate/models.py
weblate/runner.py
weblate/settings_docker.py
weblate/settings_example.py
weblate/settings_test.py
weblate/sitemaps.py
weblate/urls.py
weblate/wsgi.py
weblate/accounts/__init__.py
weblate/accounts/admin.py
weblate/accounts/apps.py
weblate/accounts/auth.py
weblate/accounts/avatar.py
weblate/accounts/captcha.py
weblate/accounts/checks.py
weblate/accounts/data.py
weblate/accounts/forms.py
weblate/accounts/middleware.py
weblate/accounts/models.py
weblate/accounts/notifications.py
weblate/accounts/password_validation.py
weblate/accounts/pipeline.py
weblate/accounts/strategy.py
weblate/accounts/tasks.py
weblate/accounts/urls.py
weblate/accounts/utils.py
weblate/accounts/views.py
weblate/accounts/management/__init__.py
weblate/accounts/management/commands/__init__.py
weblate/accounts/management/commands/dumpuserdata.py
weblate/accounts/management/commands/importuserdata.py
weblate/accounts/migrations/0001_squashed_0019_auto_20200403_2004.py
weblate/accounts/migrations/0002_profile_nearby_strings.py
weblate/accounts/migrations/0003_auto_20200630_1321.py
weblate/accounts/migrations/0004_profile_commented.py
weblate/accounts/migrations/0005_update_comment_count.py
weblate/accounts/migrations/0006_auto_20200903_0817.py
weblate/accounts/migrations/0007_auto_20200904_0840.py
weblate/accounts/migrations/0008_auto_20200923_1216.py
weblate/accounts/migrations/0009_auto_20200923_2023.py
weblate/accounts/migrations/0010_auto_20201213_1314.py
weblate/accounts/migrations/0011_auto_20210106_1903.py
weblate/accounts/migrations/0012_profile_auto_watch.py
weblate/accounts/migrations/0013_auto_20210217_1653.py
weblate/accounts/migrations/0014_auto_20210506_1421.py
weblate/accounts/migrations/0015_auto_20210512_1955.py
weblate/accounts/migrations/0016_alter_auditlog_activity.py
weblate/accounts/migrations/0017_alter_verifiedemail_email.py
weblate/accounts/migrations/0018_alter_profile_language.py
B9gemyaeix-4.14.1.dist-info/METADATA
B9gemyaeix-4.14.1.dist-info/WHEEL
B9gemyaeix-4.14.1.dist-info/entry_points.txt
B9gemyaeix-4.14.1.dist-info/top_level.txt
B9gemyaeix-4.14.1.dist-info/RECORD
