Metadata-Version: 2.1
Name: B9gemyaeix
Version: 4.14.1
Requires-Python: >=3.7
Requires-Dist: bleach (<6.0,>=3.1.1)
Requires-Dist: borgbackup (!=1.2.0,<1.3,>=1.1.11)
Requires-Dist: celery[redis] (<5.3,>=5.0.3)
Requires-Dist: charset-normalizer (<3.0,>=2.0.12)
Requires-Dist: cssselect (<1.2,>=1.0.0)
Requires-Dist: Cython (<0.30,>=0.29.14)
Requires-Dist: diff-match-patch (==20200713)
Requires-Dist: django-appconf (<1.1,>=1.0.3)
Requires-Dist: django-compressor (<5,>=2.4)
Requires-Dist: django-crispy-forms (<1.15,>=1.9.0)
Requires-Dist: django-filter (<23.0,>=2.4.0)
Requires-Dist: django-redis (<6.0,>=4.11.0)
Requires-Dist: Django[argon2] (<4.2,>=3.2)
Requires-Dist: djangorestframework (<3.14,>=3.11.0)
Requires-Dist: filelock (<3.9,>=3.7)
Requires-Dist: GitPython (<3.2,>=2.1.15)
Requires-Dist: hiredis (<2.1,>=1.0.1)
Requires-Dist: html2text (<2020.1.17,>=2019.8.11)
Requires-Dist: jsonschema (<5,>=4.5)
Requires-Dist: lxml (<4.10,>=4.9.1)
Requires-Dist: misaka (<2.2,>=2.1.0)
Requires-Dist: openpyxl (!=3.0.2,<3.1,>=2.6.0)
Requires-Dist: packaging (<22.0,>=20.5)
Requires-Dist: Pillow (<10.0,>=9.0.0)
Requires-Dist: pyahocorasick (<1.5,>=1.4)
Requires-Dist: pycairo (>=1.15.3)
Requires-Dist: Pygments (<3.0,>=2.6.0)
Requires-Dist: pygobject (>=3.34.0)
Requires-Dist: pyicumessageformat (<1.1,>=1.0.0)
Requires-Dist: pyparsing (<3.1,>=3.0.7)
Requires-Dist: python-dateutil (>=2.8.1)
Requires-Dist: python-redis-lock (<3.8,>=3.6.0)
Requires-Dist: rapidfuzz (<3.0,>=2.6.0)
Requires-Dist: requests (<2.29,>=2.26.0)
Requires-Dist: sentry-sdk (<2,>=1.6)
Requires-Dist: siphashc (<3.0,>=1.2)
Requires-Dist: social-auth-app-django (==5.0.0)
Requires-Dist: social-auth-core (==4.3.0)
Requires-Dist: translate-toolkit (<3.8,>=3.7.2)
Requires-Dist: translation-finder (<3.0,>=2.14)
Requires-Dist: user-agents (<2.3,>=2.0)
Requires-Dist: weblate-language-data (>=2022.7)
Requires-Dist: weblate-schemas (==2022.1)
Requires-Dist: importlib-metadata (<5,>=4.12) ; python_version < "3.8"
Provides-Extra: amazon
Requires-Dist: boto3 (<1.25.0,>=1.19.0) ; extra == 'amazon'
Provides-Extra: antispam
Requires-Dist: python-akismet (<0.5,>=0.4.2) ; extra == 'antispam'
Provides-Extra: fluent
Requires-Dist: fluent.syntax (<0.19,>=0.18.1) ; extra == 'fluent'
Provides-Extra: gerrit
Requires-Dist: git-review (>=1.27.0) ; extra == 'gerrit'
Provides-Extra: google
Requires-Dist: google-cloud-translate (<3.9.0,>=3.0.0) ; extra == 'google'
Provides-Extra: ini
Requires-Dist: iniparse (==0.5) ; extra == 'ini'
Provides-Extra: ldap
Requires-Dist: django-auth-ldap (<4.2.0,>=1.3.0) ; extra == 'ldap'
Provides-Extra: msterminology
Requires-Dist: zeep (<4.2.0,>=3.2.0) ; extra == 'msterminology'
Provides-Extra: mercurial
Requires-Dist: Mercurial (>=5.2) ; extra == 'mercurial'
Provides-Extra: mysql
Requires-Dist: mysqlclient (>=2.0.1) ; extra == 'mysql'
Provides-Extra: ocr
Requires-Dist: tesserocr (>=2.3.0) ; extra == 'ocr'
Provides-Extra: openidconnect
Requires-Dist: social-auth-core[openidconnect] (==4.3.0) ; extra == 'openidconnect'
Provides-Extra: php
Requires-Dist: phply (==1.2.5) ; extra == 'php'
Provides-Extra: postgres
Requires-Dist: psycopg2-binary (<2.10.0,>=2.8.0) ; extra == 'postgres'
Provides-Extra: saml
Requires-Dist: python3-saml (>=1.2.1) ; extra == 'saml'
Provides-Extra: subtitles
Requires-Dist: aeidon (<1.12.0,>=1.9.0) ; extra == 'subtitles'
Provides-Extra: yaml
Requires-Dist: ruamel.yaml (<0.18.0,>=0.16.0) ; extra == 'yaml'
Provides-Extra: all
Requires-Dist: aeidon (<1.12.0,>=1.9.0) ; extra == 'all'
Requires-Dist: boto3 (<1.25.0,>=1.19.0) ; extra == 'all'
Requires-Dist: django-auth-ldap (<4.2.0,>=1.3.0) ; extra == 'all'
Requires-Dist: fluent.syntax (<0.19,>=0.18.1) ; extra == 'all'
Requires-Dist: git-review (>=1.27.0) ; extra == 'all'
Requires-Dist: google-cloud-translate (<3.9.0,>=3.0.0) ; extra == 'all'
Requires-Dist: iniparse (==0.5) ; extra == 'all'
Requires-Dist: Mercurial (>=5.2) ; extra == 'all'
Requires-Dist: phply (==1.2.5) ; extra == 'all'
Requires-Dist: psycopg2-binary (<2.10.0,>=2.8.0) ; extra == 'all'
Requires-Dist: python-akismet (<0.5,>=0.4.2) ; extra == 'all'
Requires-Dist: python3-saml (>=1.2.1) ; extra == 'all'
Requires-Dist: ruamel.yaml (<0.18.0,>=0.16.0) ; extra == 'all'
Requires-Dist: social-auth-core[openidconnect] (==4.3.0) ; extra == 'all'
Requires-Dist: tesserocr (>=2.3.0) ; extra == 'all'
Requires-Dist: zeep (<4.2.0,>=3.2.0) ; extra == 'all'
Provides-Extra: zxcvbn
Requires-Dist: django-zxcvbn-password (==2.1.1) ; extra == 'zxcvbn'
